setup.cfg
setup.py
collective/__init__.py
collective.jqganalytics.egg-info/PKG-INFO
collective.jqganalytics.egg-info/SOURCES.txt
collective.jqganalytics.egg-info/dependency_links.txt
collective.jqganalytics.egg-info/namespace_packages.txt
collective.jqganalytics.egg-info/not-zip-safe
collective.jqganalytics.egg-info/requires.txt
collective.jqganalytics.egg-info/top_level.txt
collective/jqganalytics/__init__.py
collective/jqganalytics/configlet.py
collective/jqganalytics/configure.zcml
collective/jqganalytics/exportimport.py
collective/jqganalytics/interfaces.py
collective/jqganalytics/utility.py
collective/jqganalytics/variable.py
collective/jqganalytics/browser/__init__.py
collective/jqganalytics/browser/configure.zcml
collective/jqganalytics/browser/google-analytics-icon.png
collective/jqganalytics/browser/jquery.google-analytics.js
collective/jqganalytics/browser/viewlets.py
collective/jqganalytics/form/__init__.py
collective/jqganalytics/form/configure.zcml
collective/jqganalytics/form/field.py
collective/jqganalytics/form/interfaces.py
collective/jqganalytics/form/widget.py
collective/jqganalytics/profiles/default/actionicons.xml
collective/jqganalytics/profiles/default/componentregistry.xml
collective/jqganalytics/profiles/default/controlpanel.xml
collective/jqganalytics/profiles/default/export_steps.xml
collective/jqganalytics/profiles/default/import_steps.xml
collective/jqganalytics/profiles/default/jsregistry.xml
collective/jqganalytics/profiles/tests/jqganalytics.xml
docs/HISTORY
docs/LICENSE
docs/README
docs/TODO