Metadata-Version: 1.0
Name: collective.jqganalytics
Version: 1.1.1
Summary: A jQuery based load and set of Google Analytics
Home-page: http://plone.org/products/collective.jqganalytics/
Author: Benjamin Liles
Author-email: bliles@library.tamu.edu
License: ZPL
Keywords: plone analytics
Platform: UNKNOWN
Classifier: Framework :: Plone
Classifier: Programming Language :: Python
Classifier: Topic :: Software Development :: Libraries :: Python Modules
